tamilrulepy/__init__.py
tamilrulepy/meymayakkam.py
tolkapy-0.0.101.dist-info/METADATA
tolkapy-0.0.101.dist-info/WHEEL
tolkapy-0.0.101.dist-info/top_level.txt
tolkapy-0.0.101.dist-info/RECORD
