Metadata-Version: 2.1
Name: tolkapy
Version: 0.0.101
Summary: Tolkapy is a python package known earlier as tamilrulepy 
Author-email: "Dr.Sathiyaraj Thangasamy" <sathiyarajt@skacas.ac.in>, Parameshwar Arunachalam <parameshwar273@gmail.com>, Boopalan S <boopalan28012003@gmail.com>, Hariharan Umapathi <smarthariharan28@gmail.com>, Infofarmer <tha.uzhavan@gmail.com>, Syed Jafer K <contact.syedjafer@gmail.com>, Kamalakkannan P <kkannan.ps.2004@gmail.com>
Requires-Python: >=3.6
Requires-Dist: Open-Tamil >=1.1
